azure_ad_auth/__init__.py
azure_ad_auth/backends.py
azure_ad_auth/urls.py
azure_ad_auth/utils.py
azure_ad_auth/views.py
django_azure_ad_auth_redux-1.5.26.dist-info/METADATA
django_azure_ad_auth_redux-1.5.26.dist-info/WHEEL
django_azure_ad_auth_redux-1.5.26.dist-info/licenses/LICENSE
django_azure_ad_auth_redux-1.5.26.dist-info/RECORD
