Metadata-Version: 2.4
Name: django-azure-ad-auth-redux
Version: 1.5.26
Summary: Authenticate users using Azure Active Directory.
Author-email: Scott Sharkey <scott.sharkey@rsginc.com>
License-Expression: MIT
License-File: LICENSE
Keywords: Python, Active Directory, Django
Classifier: Development Status :: 5 - Production/Stable
Classifier: Environment :: Web Environment
Classifier: Framework :: Django
Classifier: Framework :: Django :: 3.2
Classifier: Intended Audience :: Developers
Classifier: License :: OSI Approved :: BSD License
Classifier: Natural Language :: English
Classifier: Operating System :: OS Independent
Classifier: Operating System :: POSIX
Classifier: Operating System :: Unix
Classifier: Programming Language :: Python
Classifier: Programming Language :: Python :: 3
Classifier: Programming Language :: Python :: 3.11
Classifier: Programming Language :: Python :: 3.12
Classifier: Topic :: Software Development
Requires-Python: <4,>=3.12
Requires-Dist: cryptography>=44.0.2
Requires-Dist: lxml>=5.0.1
Requires-Dist: pyjwt>=2.10.1
Requires-Dist: requests>=2.32.3
